{"events_2023-04_index.md":"77709723","events_2022-12_index.md":"fc21f432","events_2023-06_23_index.md":"0cdc6ac3","events_2023-03_15_index.md":"4f6fdf37","events_2023-04_18_index.md":"e1f3eb7c","events_2023-05_21_index.md":"ce296f72","events_2023-03_13_index.md":"991699d6","events_2023-01_index.md":"f67de522","events_2023-01_5_index.md":"389099a5","events_2023-03_index.md":"9748237e","events_2023-02_index.md":"b51019cd","events_2023-04_17_index.md":"c1ea6303","events_2023-01_4_index.md":"e8e93520","events_2023-03_11_index.md":"d9c866d5","events_2023-02_9_index.md":"840c1239","events_2023-01_3_index.md":"1413e82f","events_2023-05_index.md":"6eb0b3b4","readme.md":"3c3cc959","events_2023-03_14_index.md":"48928acd","events_2022-12_2_index.md":"7f58face","events_index.md":"91a6d7d0","events_2023-05_20_index.md":"6abc04d1","events_2023-06_24_index.md":"382c0436","events_2023-01_6_index.md":"f674e302","events_2022-12_1_index.md":"bdff2923","events_2023-02_10_index.md":"63702ff7","events_2023-02_7_index.md":"fa8d43eb","events_2023-05_22_index.md":"cea993be","events_2023-04_19_index.md":"4ef3f898","events_2023-06_index.md":"3d9d2926","events_2023-04_16_index.md":"f32fbf10","events_2023-02_8_index.md":"c25faebe","events_2023-03_12_index.md":"5b885eb5","changelog.md":"268513fd","exp_fleck_index.md":"16ae793d","exp_index.md":"13f3454b","exp_wave_index.md":"f0eb5236","exp_simplex_index.md":"367ff09e","exp_blob_index.md":"d84b8434","exp_hydra_index.md":"21530336","index.md":"173b58c5"}
